{"version":{"pluginId":"default","version":"current","label":"Suivant","banner":null,"badge":false,"noIndex":false,"className":"docs-version-current","isLast":true,"docsSidebars":{"tutorialSidebar":[{"type":"link","label":"Introduction","href":"/fr/docs/intro","docId":"intro","unlisted":false},{"type":"link","label":"Démarrage rapide","href":"/fr/docs/quickstart","docId":"Quickstart","unlisted":false},{"type":"category","label":"Comment traduire","items":[{"type":"link","label":"Configuration","href":"/fr/docs/configuration","docId":"HowToTranslate/configuration","unlisted":false},{"type":"link","label":"Translation Files Management","href":"/fr/docs/translation-files-management","docId":"HowToTranslate/translationFilesManagement","unlisted":false},{"type":"category","label":"SDK","items":[{"type":"link","label":"SDK Overview","href":"/fr/docs/HowToTranslate/sdk/quickstart","docId":"HowToTranslate/sdk/quickstart","unlisted":false},{"type":"link","label":"How to set up GitHub Action","href":"/fr/docs/HowToTranslate/sdk/github-action","docId":"HowToTranslate/sdk/github-action","unlisted":false},{"type":"link","label":"Full Example","href":"/fr/docs/SDK","docId":"HowToTranslate/sdk/example","unlisted":false}],"collapsed":true,"collapsible":true},{"type":"category","label":"CLI","items":[{"type":"link","label":"CLI User Guide","href":"/fr/docs/CLI","docId":"HowToTranslate/cli/cli-quickstart","unlisted":false}],"collapsed":true,"collapsible":true},{"type":"category","label":"Github App","items":[{"type":"link","label":"How automated translations are managed","href":"/fr/docs/githubApp","docId":"HowToTranslate/github/githubApp","unlisted":false},{"type":"link","label":"One Time Translation","href":"/fr/docs/one-time-translation","docId":"HowToTranslate/github/oneTimeTranslation","unlisted":false}],"collapsed":true,"collapsible":true}],"collapsed":true,"collapsible":true},{"type":"category","label":"Tutoriel","items":[{"type":"link","label":"Traduire docusaurus","href":"/fr/docs/Tutorial - Extras/Translate docusaurus","docId":"Tutorial - Extras/Translate docusaurus","unlisted":false}],"collapsed":true,"collapsible":true},{"type":"link","label":"FAQ","href":"/fr/docs/FAQ","docId":"FAQ","unlisted":false}]},"docs":{"FAQ":{"id":"FAQ","title":"FAQ","description":"Frequently Asked Questions","sidebar":"tutorialSidebar"},"HowToTranslate/cli/cli-quickstart":{"id":"HowToTranslate/cli/cli-quickstart","title":"CLI User Guide","description":"Learn how to use Frenglish's CLI to streamline your translation workflow","sidebar":"tutorialSidebar"},"HowToTranslate/configuration":{"id":"HowToTranslate/configuration","title":"Configuration","description":"How to configure translation settings","sidebar":"tutorialSidebar"},"HowToTranslate/github/githubApp":{"id":"HowToTranslate/github/githubApp","title":"How automated translations are managed","description":"How github app manages your locale files","sidebar":"tutorialSidebar"},"HowToTranslate/github/oneTimeTranslation":{"id":"HowToTranslate/github/oneTimeTranslation","title":"One Time Translation","description":"One Time Translation","sidebar":"tutorialSidebar"},"HowToTranslate/sdk/example":{"id":"HowToTranslate/sdk/example","title":"Full Example","description":"Example use case for SDK","sidebar":"tutorialSidebar"},"HowToTranslate/sdk/github-action":{"id":"HowToTranslate/sdk/github-action","title":"How to set up GitHub Action","description":"This guide will walk you through the process of setting up a GitHub Action to automatically translate your repository's content using the Frenglish SDK.","sidebar":"tutorialSidebar"},"HowToTranslate/sdk/quickstart":{"id":"HowToTranslate/sdk/quickstart","title":"SDK Overview","description":"Introduction","sidebar":"tutorialSidebar"},"HowToTranslate/supported-file-types":{"id":"HowToTranslate/supported-file-types","title":"Supported File Types","description":"Supported file types"},"HowToTranslate/translationFilesManagement":{"id":"HowToTranslate/translationFilesManagement","title":"Translation Files Management","description":"How to structure translation files","sidebar":"tutorialSidebar"},"intro":{"id":"intro","title":"Introduction","description":"Frenglish is designed to help your business enter new markets quickly with automated translations.","sidebar":"tutorialSidebar"},"Quickstart":{"id":"Quickstart","title":"Démarrage rapide","description":"Quickstart guide","sidebar":"tutorialSidebar"},"Tutorial - Extras/Translate docusaurus":{"id":"Tutorial - Extras/Translate docusaurus","title":"Traduire docusaurus","description":"Pour un exemple de structuration de l'i18n avec Docusaurus, consultez les docs de Frenglish.","sidebar":"tutorialSidebar"}}}}